enthusiast_source_woocommerce/__init__.py
enthusiast_source_woocommerce/source.py
enthusiast_source_woocommerce-1.2.0.dist-info/METADATA
enthusiast_source_woocommerce-1.2.0.dist-info/WHEEL
enthusiast_source_woocommerce-1.2.0.dist-info/RECORD
